ds_core/__init__.py
ds_core/config.py
ds_core/dataset.py
ds_core/features.py
ds_core/plots.py
ds_core/modeling/__init__.py
ds_core/modeling/predict.py
ds_core/modeling/train.py
mnist_mlops_lib-0.0.1.dev1.dist-info/WHEEL
mnist_mlops_lib-0.0.1.dev1.dist-info/METADATA
mnist_mlops_lib-0.0.1.dev1.dist-info/RECORD
