Metadata-Version: 2.4
Name: mnist-mlops-lib
Version: 0.0.1.dev1
Summary: MNIST digit recognition project
Author: lev antipov
Requires-Python: >=3.10
Classifier: Programming Language :: Python :: 3
Requires-Dist: loguru
Requires-Dist: mkdocs
Requires-Dist: pip
Requires-Dist: pytest
Requires-Dist: python-dotenv
Requires-Dist: ruff
Requires-Dist: tqdm
Requires-Dist: typer
Requires-Dist: numpy
Requires-Dist: scikit-learn
Requires-Dist: matplotlib
Requires-Dist: pillow
Requires-Dist: dvc
Requires-Dist: pyyaml
